{
  "usesTypeScript": false,
  "usesStyledComponents": true,
  "testLibrary": "Testing Library",
  "component": {
    "default": {
      "customTemplates": {
        "component": "templates/default/TemplateName.jsx",
        "style": "templates/default/TemplateName.styled.jsx",
        "lazy": "templates/default/TemplateName.lazy.jsx",
        "index": "templates/default/index.jsx"
      },
      "path": "src/components",
      "withStyle": true,
      "withTest": false,
      "withStory": false,
      "withLazy": false,
      "withIndex": true
    },
    "page": {
      "customTemplates": {
        "component": "templates/page/TemplateName.jsx",
        "lazy": "templates/page/TemplateName.lazy.jsx",
        "style": "templates/page/TemplateName.styled.jsx",
        "index": "templates/page/index.jsx"
      },
      "path": "src/pages",
      "withLazy": true,
      "withStory": false,
      "withStyle": true,
      "withTest": false,
      "withIndex": true
    },
    "layout": {
      "customTemplates": {
        "component": "templates/layout/TemplateName.jsx",
        "index": "templates/layout/index.jsx"
      },
      "path": "src/layouts",
      "withIndex": true
    },
    "redux": {
      "customTemplates": {
        "component": "templates/redux/TemplateNameSlice.js",
        "actions": "templates/redux/TemplateNameActions.js"
      },
      "path": "src/app/features",
      "withActions": true
    }
  }
}
